grebes/__init__.py
grebes/__main__.py
grebes/auditor.py
grebes/cli.py
grebes-0.1.1.dist-info/licenses/LICENSE
grebes-0.1.1.dist-info/METADATA
grebes-0.1.1.dist-info/WHEEL
grebes-0.1.1.dist-info/entry_points.txt
grebes-0.1.1.dist-info/top_level.txt
grebes-0.1.1.dist-info/RECORD
