Metadata-Version: 2.4
Name: grebes
Version: 0.1.1
Summary: 🕵️‍♂️ Grebes: lightweight, nature-inspired data auditor
Author: Akash Nath
Requires-Python: >=3.7
License-File: LICENSE
Requires-Dist: pandas>=1.0.0
Requires-Dist: numpy>=1.18.0
Requires-Dist: openpyxl>=3.0.0
Requires-Dist: rich>=10.0.0
Dynamic: author
Dynamic: description
Dynamic: description-content-type
Dynamic: license-file
Dynamic: requires-dist
Dynamic: requires-python
Dynamic: summary
